pangeamt_tea/__init__.py
pangeamt_tea/dataset_cleaner.py
pangeamt_tea/console_scripts/__init__.py
pangeamt_tea/console_scripts/tea.py
pangeamt_tea/console_scripts/tea_test.py
pangeamt_tea/project/__init__.py
pangeamt_tea/project/config.py
pangeamt_tea/project/project.py
pangeamt_tea/project/workflow/__init__.py
pangeamt_tea/project/workflow/config.py
pangeamt_tea/project/workflow/workflow.py
pangeamt_tea/project/workflow/stage/__init__.py
pangeamt_tea/project/workflow/stage/base_stage.py
pangeamt_tea/project/workflow/stage/clean_stage.py
pangeamt_tea/project/workflow/stage/eval_stage.py
pangeamt_tea/project/workflow/stage/init_stage.py
pangeamt_tea/project/workflow/stage/prepare_stage.py
pangeamt_tea/project/workflow/stage/publish_stage.py
pangeamt_tea/project/workflow/stage/stage_factory.py
pangeamt_tea/project/workflow/stage/train_stage.py
pangeamt_tea-0.2.34.data/scripts/seeded_shuffle.sh
pangeamt_tea-0.2.34.dist-info/METADATA
pangeamt_tea-0.2.34.dist-info/WHEEL
pangeamt_tea-0.2.34.dist-info/entry_points.txt
pangeamt_tea-0.2.34.dist-info/top_level.txt
pangeamt_tea-0.2.34.dist-info/RECORD
