Metadata-Version: 2.1
Name: pangeamt-tea
Version: 0.2.34
Summary: TEA - Translation Engine Architect
Home-page: UNKNOWN
Author: Pangeamt
License: UNKNOWN
Platform: UNKNOWN
Requires-Python: >=3.7
Requires-Dist: PyYAML
Requires-Dist: aiohttp
Requires-Dist: aiounittest
Requires-Dist: asyncclick
Requires-Dist: autoclass
Requires-Dist: nteu-corporate-engine (>=0.1.6)
Requires-Dist: pangeamt-nlp (>=0.9.0)
Requires-Dist: pathos
Requires-Dist: sacrebleu
